dataset_with_logits/__init__.py
dataset_with_logits/prediction_dataset.py
dataset_with_logits/datasets/__init__.py
dataset_with_logits/datasets/base.py
dataset_with_logits/datasets/imagenet.py
dataset_with_logits/datasets/simple.py
dataset_with_logits/utils/__init__.py
dataset_with_logits/utils/download.py
dataset_with_logits/utils/validation.py
dataset_with_logits-1.0.3.dist-info/METADATA
dataset_with_logits-1.0.3.dist-info/WHEEL
dataset_with_logits-1.0.3.dist-info/top_level.txt
dataset_with_logits-1.0.3.dist-info/RECORD
