Metadata-Version: 2.4
Name: dataset-with-logits
Version: 1.0.3
Summary: PyTorch datasets with pre-computed model logits for efficient research
Author-email: ViGeng <your.email@example.com>
License: MIT
Project-URL: Homepage, https://github.com/ViGeng/predictions-on-datasets
Project-URL: Repository, https://github.com/ViGeng/predictions-on-datasets
Project-URL: Documentation, https://github.com/ViGeng/predictions-on-datasets#readme
Project-URL: Bug Tracker, https://github.com/ViGeng/predictions-on-datasets/issues
Keywords: pytorch,imagenet,cifar,dataset,computer-vision,machine-learning,knowledge-distillation,deep-learning,logits,pretrained-models
Classifier: Development Status :: 4 - Beta
Classifier: Intended Audience :: Developers
Classifier: Intended Audience :: Science/Research
Classifier: License :: OSI Approved :: MIT License
Classifier: Operating System :: OS Independent
Classifier: Programming Language :: Python :: 3
Classifier: Programming Language :: Python :: 3.8
Classifier: Programming Language :: Python :: 3.9
Classifier: Programming Language :: Python :: 3.10
Classifier: Programming Language :: Python :: 3.11
Classifier: Programming Language :: Python :: 3.12
Classifier: Topic :: Scientific/Engineering :: Artificial Intelligence
Classifier: Topic :: Software Development :: Libraries :: Python Modules
Requires-Python: >=3.8
Requires-Dist: torch>=1.7.0
Requires-Dist: torchvision>=0.8.0
Requires-Dist: pandas>=1.1.0
Requires-Dist: pillow>=8.0.0
Requires-Dist: huggingface_hub>=0.16.0
Provides-Extra: dev
Requires-Dist: pytest>=6.0; extra == "dev"
Requires-Dist: pytest-cov; extra == "dev"
Requires-Dist: black; extra == "dev"
Requires-Dist: flake8; extra == "dev"
Requires-Dist: mypy; extra == "dev"
Requires-Dist: twine; extra == "dev"
Requires-Dist: build; extra == "dev"
